PyBitCrypt/__init__.py
PyBitCrypt/decrypter.py
PyBitCrypt/encrypter.py
PyBitCrypt/pbc.py
PyBitCrypt-3.0.1.dist-info/LICENSE
PyBitCrypt-3.0.1.dist-info/METADATA
PyBitCrypt-3.0.1.dist-info/WHEEL
PyBitCrypt-3.0.1.dist-info/top_level.txt
PyBitCrypt-3.0.1.dist-info/RECORD
