Metadata-Version: 2.2
Name: PyBitCrypt
Version: 3.0.1
Summary: A simple encrypting and decrypting module.
Author-email: Daniel Drury <daniel-drury@outlook.com>
Project-URL: Homepage, https://github.com/Chickpeaplane/PyBitCrypt
Project-URL: Bug Tracker, https://github.com/Chickpeaplane/PyBitCrypt/issues
Classifier: Programming Language :: Python :: 3
Classifier: License :: OSI Approved :: MIT License
Classifier: Operating System :: OS Independent
Requires-Python: >=3.8
License-File: LICENSE
